setup.py
src/ua2/__init__.py
src/ua2.fabdep.egg-info/PKG-INFO
src/ua2.fabdep.egg-info/SOURCES.txt
src/ua2.fabdep.egg-info/dependency_links.txt
src/ua2.fabdep.egg-info/eager_resources.txt
src/ua2.fabdep.egg-info/namespace_packages.txt
src/ua2.fabdep.egg-info/not-zip-safe
src/ua2.fabdep.egg-info/top_level.txt
src/ua2/fabdep/__init__.py
src/ua2/fabdep/tasks.py
src/ua2/fabdep/vc.py