Metadata-Version: 1.0
Name: ua2.fabdep
Version: 0.0.2
Summary: Fabric management for external source code repositories.
Home-page: https://bitbucket.org/ua2web/ua2.fabdep
Author: AVK
Author-email: alex@ua2web.com
License: BSD License
Platform: UNKNOWN
